semremover/__init__.py
semremover/__main__.py
semremover/models/__init__.py
semremover/models/lama.py
semremover/models/maskformer.py
semremover/models/semremover.py
semremover/models/utils.py
semremover-1.0.0.dist-info/LICENSE
semremover-1.0.0.dist-info/METADATA
semremover-1.0.0.dist-info/WHEEL
semremover-1.0.0.dist-info/top_level.txt
semremover-1.0.0.dist-info/RECORD
