Metadata-Version: 2.1
Name: semremover
Version: 1.0.0
Summary: semantic object removal made easy.
Author-email: Jesse Visser <jssvssr2000@gmail.com>
Project-URL: Homepage, https://github.com/Jessseee/semantic-object-removal
Project-URL: Bug Tracker, https://github.com/Jessseee/semantic-object-removal/issues
Classifier: Programming Language :: Python :: 3
Classifier: License :: OSI Approved :: MIT License
Classifier: Operating System :: OS Independent
Classifier: Environment :: GPU :: NVIDIA CUDA
Requires-Python: >=3.10
License-File: LICENSE
